transformers_gradients/__init__.py
transformers_gradients/api.py
transformers_gradients/assertions.py
transformers_gradients/functions.py
transformers_gradients/hyperparameters.py
transformers_gradients/lib_types.py
transformers_gradients/plotting.py
transformers_gradients/py.typed
transformers_gradients/utils.py
transformers_gradients/tasks/__init__.py
transformers_gradients/tasks/question_answering.py
transformers_gradients/tasks/text_2_text.py
transformers_gradients/tasks/text_classification.py
transformers_gradients/tasks/text_generation.py
transformers_gradients/tasks/token_classification.py
transformers_gradients/tasks/translation.py
transformers_gradients/templates/heatmap.html
transformers_gradients-0.0.29.dist-info/WHEEL
transformers_gradients-0.0.29.dist-info/METADATA
transformers_gradients-0.0.29.dist-info/RECORD
