Metadata-Version: 2.1
Name: transformers_gradients
Version: 0.0.29
Summary: Gradient-based XAI methods for TensorFlow transformers.
Keywords: explainable ai,xai,machine learning,deep learning
Author-email: Artem Sereda <artem.sereda@campus.tu-berlin.de>
Maintainer-email: Artem Sereda <artem.sereda@campus.tu-berlin.de>
Requires-Python: >=3.8
Classifier: Development Status :: 3 - Alpha
Classifier: Intended Audience :: Education
Classifier: Intended Audience :: Science/Research
Classifier: Intended Audience :: Developers
Classifier: Programming Language :: Python :: 3 :: Only
Classifier: Topic :: Software Development :: Libraries :: Python Modules
Classifier: Topic :: Scientific/Engineering :: Artificial Intelligence
Requires-Dist: tensorflow >= 2.10.0; sys_platform != 'darwin'
Requires-Dist: tensorflow_macos >= 2.10.0; sys_platform == 'darwin'
Requires-Dist: tensorflow_probability >= 0.18.0
Requires-Dist: transformers
Requires-Dist: pydantic
Requires-Dist: jinja2
Project-URL: Homepage, https://github.com/aaarrti/TransformersXGradients
